TP2_OC-{CAMINHO_DE_DADOS_RISC_V}/Verilog_Codigo/Data_Memory.v
module Data_Memory (clk,Endereco,Write_Data,Mem_Write,Mem_Read,Read_Data);
    input wire clk;
    input wire [31:0] Endereco;
    input wire [31:0] Write_Data;
    input wire Mem_Write;
    input wire Mem_Read;
    output reg [31:0] Read_Data;
    reg [31:0] vetor_memoria [0:54];  // Vetor que representa a memória de dados.

    // Carrega dados da memória de um arquivo.
    initial begin
        $readmemb("Memoria_Dados.bin", vetor_memoria);
    end

    always @(posedge clk) begin
        if (Mem_Write) //Se 1, escreve na posição do vetor, do endereço especifico.
            vetor_memoria[Endereco[7:0]] <= Write_Data;
    end

    always @(*) begin
        if (Mem_Read) //Se 1, le um dado.
            Read_Data = vetor_memoria[Endereco[7:0]];
        else
            Read_Data = 32'b0;
    end
endmodule

TP2_OC-{CAMINHO_DE_DADOS_RISC_V}/Verilog_Codigo/ALU.v
module ALU(X, Y, ALUop, Resultado_ALU, zero);
    input [31:0] X, Y;
    input [2:0] ALUop;
    output reg [31:0] Resultado_ALU;
    output zero;

    assign zero = (Resultado_ALU == 0) ? 1 : 0;

    always @(*) begin
        case (ALUop)// Seleciona o tipo de operação.
            3'b000: Resultado_ALU = X & Y;  // AND
            3'b001: Resultado_ALU = X | Y;  // OR
            3'b010: Resultado_ALU = X + Y;  // ADD
            3'b011: Resultado_ALU = X - Y;  // SUB
            3'b100: Resultado_ALU = X >> Y; // SRL
            default: Resultado_ALU = 0;
        endcase
    end
endmodule

TP2_OC-{CAMINHO_DE_DADOS_RISC_V}/Verilog_Codigo/Imm_gen.v
module Imm_gen (Instrucao,saida_Imm);
    input  [31:0] Instrucao;
    output reg [31:0] saida_Imm;


// tipo I
wire [31:0] saida_Imm_I = { {20{Instrucao[31]}}, Instrucao[31:20] };

// tipo S
wire [31:0] saida_Imm_S = { {20{Instrucao[31]}}, Instrucao[31:25], Instrucao[11:7] };

// tipo B
wire [31:0] saida_Imm_B = { {19{Instrucao[31]}}, Instrucao[31], Instrucao[7], Instrucao[30:25], Instrucao[11:8], 1'b0 };

// Seleção do imediato.
always @(*) begin
    case (Instrucao[6:0])
        7'b0000011: saida_Imm = saida_Imm_I;  //  tipo I
        7'b0100011: saida_Imm = saida_Imm_S;  //  tipo S 
        7'b1100011: saida_Imm = saida_Imm_B;  //  tipo B
        7'b0010011: saida_Imm = saida_Imm_I;  //  tipo I
        default:    saida_Imm = 32'b0;        // 0s
    endcase
end

endmodule

TP2_OC-{CAMINHO_DE_DADOS_RISC_V}/Verilog_Codigo/Banco_de_Registradores.v
module Banco_de_Registradores(clk,reset,RegWrite,rs1,rs2,rd,Write_Data,Register1,Register2);
    input clk;
    input reset;
    input RegWrite;
    input [4:0] rs1, rs2, rd;
    input [31:0] Write_Data;
    output [31:0] Register1, Register2;
    reg [31:0] reg_vetor [31:0]; // Vetor com 32 registradores.
    integer i;
    //Os 2 registradores usado nas operações.
    assign Register1 = reg_vetor[rs1];
    assign Register2 = reg_vetor[rs2];

    //Inicia os registradores como 0.
    always @(posedge clk or posedge reset) begin
        if (reset) begin //Reseta todos os registradores para 0.
            for (i = 0; i < 32; i = i + 1) begin
                reg_vetor[i] <= 0;
            end
        end else if (RegWrite) begin // Se RegWrite for 1, escreve o resultado de uma operação no endereço de rd.
            reg_vetor[rd] <= Write_Data;
        end
    end

endmodule

TP2_OC-{CAMINHO_DE_DADOS_RISC_V}/Verilog_Codigo/Unit_Control.v
module Unit_Control (opcode,funct3,funct7,ALUop,Mem_Read,Mem_Write,RegWrite,ALU_src,Mem_to_Reg,branch);
    input [6:0] opcode;
    input [2:0] funct3;
    input [6:0] funct7;
    output reg [2:0] ALUop;
    output reg Mem_Read;
    output reg Mem_Write;
    output reg RegWrite;
    output reg ALU_src;
    output reg Mem_to_Reg;
    output reg branch;

    always @(*) begin
        // Inicializar os sinais de controle
        ALUop = 3'b000;
        Mem_Read = 0;
        Mem_Write = 0;
        RegWrite = 0;
        ALU_src = 0;
        Mem_to_Reg = 0;
        branch = 0;

        case (opcode)
            7'b0000011: begin  // LB
                ALUop = 3'b010; 
                Mem_Read = 1;
                Mem_Write = 0;
                RegWrite = 1;
                ALU_src = 1;
                Mem_to_Reg = 1;
                branch = 0;
            end
            7'b0100011: begin  // SB
                ALUop = 3'b010;  
                Mem_Read = 0;
                Mem_Write = 1;
                RegWrite = 0;
                ALU_src = 1;
                Mem_to_Reg = 0;
                branch = 0;
            end
            7'b1100011: begin  // BEQ
                ALUop = 3'b011;  
                Mem_Read = 0;
                Mem_Write = 0;
                RegWrite = 0;
                ALU_src = 0;
                Mem_to_Reg = 0;
                branch = 1;
            end
            7'b0010011: begin  // TIPO I
                case (funct3)
                    3'b000: ALUop = 3'b010;  // ADDI
                    3'b110: ALUop = 3'b001;  // ORI
                    3'b101: ALUop = 3'b100;  // SRL
                    default: ALUop = 3'b000;
                endcase
                Mem_Read = 0;
                Mem_Write = 0;
                RegWrite = 1;
                ALU_src = 1;
                Mem_to_Reg = 0;
                branch = 0;
            end
             7'b0110011: begin  // TIPO R
                case ({funct7, funct3})
                    {7'b0000000, 3'b000}: ALUop = 3'b010;  // ADD
                    {7'b0100000, 3'b000}: ALUop = 3'b011;  // SUB
                    {7'b0000000, 3'b111}: ALUop = 3'b101;  // AND
                    default: ALUop = 3'b000;
                endcase
                Mem_Read = 0;
                Mem_Write = 0;
                RegWrite = 1;
                ALU_src = 0;
                Mem_to_Reg = 0;
                branch = 0;
             end
            default: begin
                ALUop = 3'b000;
                Mem_Read = 0;
                Mem_Write = 0;
                RegWrite = 0;
                ALU_src = 0;
                Mem_to_Reg = 0;
                branch = 0;
            end
        endcase
    end
endmodule

TP2_OC-{CAMINHO_DE_DADOS_RISC_V}/Verilog_Codigo/Instruction_Memory.v
module Instruction_Memory(Endereco, Instrucao);
    input [31:0] Endereco;
    output reg [31:0] Instrucao;
    reg [31:0] Instruction_Mem [0:255]; // Memoria de instruções, onde as memorias do programa estao/serao armazenadas.

    initial begin 
       //Instruções que deixamos de padrão.
        Instruction_Mem[0] = 32'b00000000101100000000001110010011; // addi x7, x0, 11
        Instruction_Mem[1] = 32'b00000000000100000000000010000011; // lb x1, 1(x0) 
        Instruction_Mem[2] = 32'b00000000001000001000000100100011; // sb x2, 2(x1)
        Instruction_Mem[3] = 32'b01000000001000001000000110110011; // sub x3, x1, x2
        Instruction_Mem[4] = 32'b00000000000100010111001000110011; // and x4, x2, x1
        Instruction_Mem[5] = 32'b00000000000100001110001010010011; // ori x5, x1, 1
        Instruction_Mem[6] = 32'b00000000000100010101001100010011; // srl x6, x2, 1
        Instruction_Mem[7] = 32'b00000000000100010000000011100011; // beq x1, x2, 1


    end
    //Le uma instrução por vez.
    always @(*)begin
        Instrucao = Instruction_Mem[Endereco[7:0]];
    end
endmodule

TP2_OC-{CAMINHO_DE_DADOS_RISC_V}/Verilog_Codigo/Program_Counter.v
module Program_Counter (clk, reset, pc_next, pc);

input clk;
input reset;
input [31:0] pc_next;
output reg [31:0] pc;

always @(posedge clk or posedge reset)begin
    if(reset)begin //Zera, se reset =1.
        pc <= 0;
    end
    else begin //Se nao, pc é igual ao proximo pc.
        pc <= pc_next;
    end
end

endmodule

TP2_OC-{CAMINHO_DE_DADOS_RISC_V}/Verilog_Codigo/Caminho_de_Dados.v
module Caminho_de_Dados (clk, reset, saida_pc);

    input clk;
    input reset;
    output [31:0] saida_pc;
    //Definição de variaveis.
    wire [31:0] pc, pc_next, Instrucao, Register1, Register2, Resultado_ALU, mem_data, saida_Imm;
    wire [2:0] ALUop;
    wire zero, Mem_Read, Mem_Write, RegWrite, ALU_src, Mem_to_Reg, branch;
    //Instanciação e junção dos modulos.
    // PC Register.
    Program_Counter PC_Reg (
        .clk(clk),
        .reset(reset),
        .pc_next(pc_next),
        .pc(pc)
    );

    // Instruction Memory.
    Instruction_Memory IM (
        .Endereco(pc),
        .Instrucao(Instrucao)
    );

    // Control Unit.
    Unit_Control Control (
        .opcode(Instrucao[6:0]),
        .funct3(Instrucao[14:12]),
        .funct7(Instrucao[31:25]),
        .ALUop(ALUop),
        .Mem_Read(Mem_Read),
        .Mem_Write(Mem_Write),
        .RegWrite(RegWrite),
        .ALU_src(ALU_src),
        .Mem_to_Reg(Mem_to_Reg),
        .branch(branch)
    );

    // Banco de Registradores.
    Banco_de_Registradores RF (
        .clk(clk),
        .rs1(Instrucao[19:15]),
        .rs2(Instrucao[24:20]),
        .rd(Instrucao[11:7]),
        .Write_Data(Mem_to_Reg ? mem_data : Resultado_ALU),
        .RegWrite(RegWrite),
        .Register1(Register1),
        .Register2(Register2),
        .reset(reset)
    );

    // Immediatos.
    Imm_gen IG (
        .Instrucao(Instrucao),
        .saida_Imm(saida_Imm)
    );

    // ALU.
    ALU ALU (
        .X(Register1),
        .Y(ALU_src ? saida_Imm : Register2),
        .ALUop(ALUop),
        .Resultado_ALU(Resultado_ALU),
        .zero(zero)
    );

    // Data Memory.
    Data_Memory DM (
        .clk(clk),
        .Endereco(Resultado_ALU),
        .Write_Data(Register2),
        .Mem_Write(Mem_Write),
        .Mem_Read(Mem_Read),
        .Read_Data(mem_data)
    );

    // Logica do program counter.
    assign pc_next = (branch && zero) ? (pc + (saida_Imm << 1)) : (pc + 1);
    assign saida_pc = pc;

    
endmodule

TP2_OC-{CAMINHO_DE_DADOS_RISC_V}/Verilog_Codigo/Caminho_de_Dados_tb.v
module Testbench;

    reg clk;
    reg reset;
    wire [31:0] saida_pc;

    // Instancia o módulo Caminho_de_Dados.
    Caminho_de_Dados uut (
        .clk(clk),
        .reset(reset),
        .saida_pc(saida_pc)
    );

    // Clock.
    always begin
        #5 clk = ~clk;
    end

    // Inicialização dos sinais e execução do teste.
    initial begin
        
        // Inicializa o clock e o reset
        clk = 0;
        reset = 0;

        // Configuração para gerar o arquivo VCD
        $dumpfile("exec.vcd");   // Nome do arquivo VCD
        $dumpvars(0, Testbench);      // Adiciona todos os sinais do testbench ao arquivo VCD

        // Reset geral.
        reset = 1;
        #10;
        reset = 0;

        // Delay, para as instruções executarem.
        #200; 

        $display("Teste completo.");

        // Imprimir o conteúdo dos registradores.
        $display("==================INICIO===================");
        $display("Registrador[0]  %0d", uut.RF.reg_vetor[0]);
        $display("Registrador[1]  %0d", uut.RF.reg_vetor[1]);
        $display("Registrador[2]  %0d", uut.RF.reg_vetor[2]);
        $display("Registrador[3]  %0d", uut.RF.reg_vetor[3]);
        $display("Registrador[4]  %0d", uut.RF.reg_vetor[4]);
        $display("Registrador[5]  %0d", uut.RF.reg_vetor[5]);
        $display("Registrador[6]  %0d", uut.RF.reg_vetor[6]);
        $display("Registrador[7]  %0d", uut.RF.reg_vetor[7]);
        $display("Registrador[8]  %0d", uut.RF.reg_vetor[8]);
        $display("Registrador[9]  %0d", uut.RF.reg_vetor[9]);
        $display("Registrador[10] %0d", uut.RF.reg_vetor[10]);
        $display("Registrador[11] %0d", uut.RF.reg_vetor[11]);
        $display("Registrador[12] %0d", uut.RF.reg_vetor[12]);
        $display("Registrador[13] %0d", uut.RF.reg_vetor[13]);
        $display("Registrador[14] %0d", uut.RF.reg_vetor[14]);
        $display("Registrador[15] %0d", uut.RF.reg_vetor[15]);
        $display("Registrador[16] %0d", uut.RF.reg_vetor[16]);
        $display("Registrador[17] %0d", uut.RF.reg_vetor[17]);
        $display("Registrador[18] %0d", uut.RF.reg_vetor[18]);
        $display("Registrador[19] %0d", uut.RF.reg_vetor[19]);
        $display("Registrador[20] %0d", uut.RF.reg_vetor[20]);
        $display("Registrador[21] %0d", uut.RF.reg_vetor[21]);
        $display("Registrador[22] %0d", uut.RF.reg_vetor[22]);
        $display("Registrador[23] %0d", uut.RF.reg_vetor[23]);
        $display("Registrador[24] %0d", uut.RF.reg_vetor[24]);
        $display("Registrador[25] %0d", uut.RF.reg_vetor[25]);
        $display("Registrador[26] %0d", uut.RF.reg_vetor[26]);
        $display("Registrador[27] %0d", uut.RF.reg_vetor[27]);
        $display("Registrador[28] %0d", uut.RF.reg_vetor[28]);
        $display("Registrador[29] %0d", uut.RF.reg_vetor[29]);
        $display("Registrador[30] %0d", uut.RF.reg_vetor[30]);
        $display("Registrador[31] %0d", uut.RF.reg_vetor[31]);
        $display("===================FIM====================");

        $finish;
    end

endmodule

TP2_OC-{CAMINHO_DE_DADOS_RISC_V}/exec.vcd
$date
	Sun Aug 11 22:11:29 2024
$end
$version
	Icarus Verilog
$end
$timescale
	1s
$end
$scope module Testbench $end
$var wire 32 ! saida_pc [31:0] $end
$var reg 1 " clk $end
$var reg 1 # reset $end
$scope module uut $end
$var wire 1 " clk $end
$var wire 1 # reset $end
$var wire 32 $ saida_pc [31:0] $end
$var wire 1 % zero $end
$var wire 32 & saida_Imm [31:0] $end
$var wire 32 ' pc_next [31:0] $end
$var wire 32 ( pc [31:0] $end
$var wire 32 ) mem_data [31:0] $end
$var wire 1 * branch $end
$var wire 32 + Resultado_ALU [31:0] $end
$var wire 32 , Register2 [31:0] $end
$var wire 32 - Register1 [31:0] $end
$var wire 1 . RegWrite $end
$var wire 1 / Mem_to_Reg $end
$var wire 1 0 Mem_Write $end
$var wire 1 1 Mem_Read $end
$var wire 32 2 Instrucao [31:0] $end
$var wire 3 3 ALUop [2:0] $end
$var wire 1 4 ALU_src $end
$scope module ALU $end
$var wire 32 5 Y [31:0] $end
$var wire 1 % zero $end
$var wire 32 6 X [31:0] $end
$var wire 3 7 ALUop [2:0] $end
$var reg 32 8 Resultado_ALU [31:0] $end
$upscope $end
$scope module Control $end
$var wire 3 9 funct3 [2:0] $end
$var wire 7 : funct7 [6:0] $end
$var wire 7 ; opcode [6:0] $end
$var reg 1 4 ALU_src $end
$var reg 3 < ALUop [2:0] $end
$var reg 1 1 Mem_Read $end
$var reg 1 0 Mem_Write $end
$var reg 1 / Mem_to_Reg $end
$var reg 1 . RegWrite $end
$var reg 1 * branch $end
$upscope $end
$scope module DM $end
$var wire 32 = Endereco [31:0] $end
$var wire 1 1 Mem_Read $end
$var wire 1 0 Mem_Write $end
$var wire 1 " clk $end
$var wire 32 > Write_Data [31:0] $end
$var reg 32 ? Read_Data [31:0] $end
$upscope $end
$scope module IG $end
$var wire 32 @ saida_Imm_S [31:0] $end
$var wire 32 A saida_Imm_I [31:0] $end
$var wire 32 B saida_Imm_B [31:0] $end
$var wire 32 C Instrucao [31:0] $end
$var reg 32 D saida_Imm [31:0] $end
$upscope $end
$scope module IM $end
$var wire 32 E Endereco [31:0] $end
$var reg 32 F Instrucao [31:0] $end
$upscope $end
$scope module PC_Reg $end
$var wire 1 " clk $end
$var wire 32 G pc_next [31:0] $end
$var wire 1 # reset $end
$var reg 32 H pc [31:0] $end
$upscope $end
$scope module RF $end
$var wire 1 . RegWrite $end
$var wire 32 I Register1 [31:0] $end
$var wire 32 J Register2 [31:0] $end
$var wire 32 K Write_Data [31:0] $end
$var wire 1 " clk $end
$var wire 5 L rd [4:0] $end
$var wire 1 # reset $end
$var wire 5 M rs1 [4:0] $end
$var wire 5 N rs2 [4:0] $end
$var integer 32 O i [31:0] $end
$upscope $end
$upscope $end
$upscope $end
$enddefinitions $end
#0
$dumpvars
b100000 O
b1011 N
b0 M
b111 L
b1011 K
b0 J
b0 I
b0 H
b1 G
b101100000000001110010011 F
b0 E
b1011 D
b101100000000001110010011 C
b100000000110 B
b1011 A
b111 @
b0 ?
b0 >
b1011 =
b10 <
b10011 ;
b0 :
b0 9
b1011 8
b10 7
b0 6
b1011 5
14
b10 3
b101100000000001110010011 2
01
00
0/
1.
b0 -
b0 ,
b1011 +
0*
b0 )
b0 (
b1 '
b1011 &
0%
b0 $
1#
0"
b0 !
$end
#5
b100000 O
1"
#10
0"
0#
#15
b1 +
b1 8
b1 =
b10 K
b10 )
b10 ?
b1 5
b1 &
b1 D
1/
11
14
1.
b10 3
b10 7
b10 <
b100000000000 B
b1 @
b1 A
b1 L
b1 N
b11 ;
b10 '
b10 G
b100000000000010000011 2
b100000000000010000011 C
b100000000000010000011 F
b1 !
b1 $
b1 (
b1 E
b1 H
1"
#20
0"
#25
b100 K
b10 5
b0 )
b0 ?
b10 &
b10 D
b100 +
b100 8
b100 =
10
0/
14
0.
01
b10 3
b10 7
b10 <
b10 B
b10 @
b10 A
b10 L
b10 N
b10 -
b10 6
b10 I
b1 M
b100011 ;
b11 '
b11 G
b1000001000000100100011 2
b1000001000000100100011 C
b1000001000000100100011 F
b0 ,
b0 >
b0 J
b10 !
b10 $
b10 (
b10 E
b10 H
1"
#30
0"
#35
b10 K
b10 +
b10 8
b10 =
1.
04
00
b11 3
b11 7
b11 <
b0 5
b110000000010 B
b10000000011 @
b10000000010 A
b11 L
b100000 :
b110011 ;
b0 &
b0 D
b100 '
b100 G
b1000000001000001000000110110011 2
b1000000001000001000000110110011 C
b1000000001000001000000110110011 F
b11 !
b11 $
b11 (
b11 E
b11 H
1"
#40
0"
#45
1%
b0 K
b10 5
b0 +
b0 8
b0 =
1.
b101 3
b101 7
b101 <
b100 B
b100 @
b1 A
b100 L
b10 ,
b10 >
b10 J
b1 N
b0 -
b0 6
b0 I
b10 M
b0 :
b111 9
b101 '
b101 G
b100010111001000110011 2
b100010111001000110011 C
b100010111001000110011 F
b100 !
b100 $
b100 (
b100 E
b100 H
1"
#50
0"
#55
0%
b11 K
b1 5
b11 +
b11 8
b11 =
14
1.
b1 3
b1 7
b1 <
b100000000100 B
b101 @
b101 L
b10 -
b10 6
b10 I
b1 M
b110 9
b10011 ;
b1 &
b1 D
b110 '
b110 G
b100001110001010010011 2
b100001110001010010011 C
b100001110001010010011 F
b101 !
b101 $
b101 (
b101 E
b101 H
1"
#60
0"
#65
1%
b0 K
b0 +
b0 8
b0 =
14
1.
b100 3
b100 7
b100 <
b110 B
b110 @
b110 L
b0 -
b0 6
b0 I
b10 M
b101 9
b111 '
b111 G
b100010101001100010011 2
b100010101001100010011 C
b100010101001100010011 F
b110 !
b110 $
b110 (
b110 E
b110 H
1"
#70
0"
#75
0%
b11111111111111111111111111111110 K
b11111111111111111111111111111110 +
b11111111111111111111111111111110 8
b11111111111111111111111111111110 =
1*
04
0.
b11 3
b11 7
b11 <
b10 5
b100000000000 B
b1 @
b1 L
b0 9
b1100011 ;
b100000000000 &
b100000000000 D
b1000 '
b1000 G
b100010000000011100011 2
b100010000000011100011 C
b100010000000011100011 F
b111 !
b111 $
b111 (
b111 E
b111 H
1"
#80
0"
#85
x%
bx K
bx 5
bx +
bx 8
bx =
0*
b0 3
b0 7
b0 <
bx0 B
bx @
bx A
bx L
bx ,
bx >
bx J
bx N
bx -
bx 6
bx I
bx M
bx :
bx 9
bx ;
b0 &
b0 D
b1001 '
b1001 G
bx 2
bx C
bx F
b1000 !
b1000 $
b1000 (
b1000 E
b1000 H
1"
#90
0"
#95
b1010 '
b1010 G
b1001 !
b1001 $
b1001 (
b1001 E
b1001 H
1"
#100
0"
#105
b1011 '
b1011 G
b1010 !
b1010 $
b1010 (
b1010 E
b1010 H
1"
#110
0"
#115
b1100 '
b1100 G
b1011 !
b1011 $
b1011 (
b1011 E
b1011 H
1"
#120
0"
#125
b1101 '
b1101 G
b1100 !
b1100 $
b1100 (
b1100 E
b1100 H
1"
#130
0"
#135
b1110 '
b1110 G
b1101 !
b1101 $
b1101 (
b1101 E
b1101 H
1"
#140
0"
#145
b1111 '
b1111 G
b1110 !
b1110 $
b1110 (
b1110 E
b1110 H
1"
#150
0"
#155
b10000 '
b10000 G
b1111 !
b1111 $
b1111 (
b1111 E
b1111 H
1"
#160
0"
#165
b10001 '
b10001 G
b10000 !
b10000 $
b10000 (
b10000 E
b10000 H
1"
#170
0"
#175
b10010 '
b10010 G
b10001 !
b10001 $
b10001 (
b10001 E
b10001 H
1"
#180
0"
#185
b10011 '
b10011 G
b10010 !
b10010 $
b10010 (
b10010 E
b10010 H
1"
#190
0"
#195
b10100 '
b10100 G
b10011 !
b10011 $
b10011 (
b10011 E
b10011 H
1"
#200
0"
#205
b10101 '
b10101 G
b10100 !
b10100 $
b10100 (
b10100 E
b10100 H
1"
